pita/__init__.py
pita/api.py
pita/models.py
pita/utils.py
django_pita-1.0.0.dist-info/LICENSE
django_pita-1.0.0.dist-info/METADATA
django_pita-1.0.0.dist-info/WHEEL
django_pita-1.0.0.dist-info/top_level.txt
django_pita-1.0.0.dist-info/RECORD
