Metadata-Version: 2.1
Name: django-pita
Version: 1.0.0
Summary: Add version history to your Django models with Point in Time Architecture (type 2 slowly changing dimensions)
Author-email: Erik Umble <erikumble@gmail.com>
License: MIT License
Project-URL: Homepage, https://github.com/ErikUmble/django-pita
Keywords: django,version,tracking,PTA
Classifier: License :: OSI Approved :: MIT License
Classifier: Programming Language :: Python
Classifier: Programming Language :: Python :: 3
Requires-Python: >=3.8
License-File: LICENSE
Requires-Dist: django >=4.0.9
Provides-Extra: dev
Requires-Dist: black ; extra == 'dev'
Requires-Dist: pytest ; extra == 'dev'
Requires-Dist: pytest-django ; extra == 'dev'
Requires-Dist: factory-boy ; extra == 'dev'
Provides-Extra: drf
Requires-Dist: djangorestframework ; extra == 'drf'
